Metadata-Version: 1.0
Name: kekpack
Version: 0.1.0
Summary: A example Python package
Home-page: https://github.com/shuds13/pyexample
Author: Emil Garipov
Author-email: test@test.test
License: BSD 2-clause
Platform: UNKNOWN
